README.md
setup.py
TOPSIS_Pyaar_101803479.egg-info/PKG-INFO
TOPSIS_Pyaar_101803479.egg-info/SOURCES.txt
TOPSIS_Pyaar_101803479.egg-info/dependency_links.txt
TOPSIS_Pyaar_101803479.egg-info/entry_points.txt
TOPSIS_Pyaar_101803479.egg-info/requires.txt
TOPSIS_Pyaar_101803479.egg-info/top_level.txt
src/topsis.py