Metadata-Version: 2.1
Name: TOPSIS-Pyaar-101803479
Version: 1.0.1
Summary: A Python package implementing TOPSIS technique.
Home-page: https://pypi.org/project/TOPSIS-Pyaar-101803479
Author: Pyaar Singh
Author-email: psingh5_be18@thapar.edu
License: MIT
Platform: UNKNOWN
Classifier: License :: OSI Approved :: MIT License
Classifier: Programming Language :: Python :: 3
Classifier: Programming Language :: Python :: 3.4
Classifier: Programming Language :: Python :: 3.5
Classifier: Programming Language :: Python :: 3.6
Classifier: Programming Language :: Python :: 3.7
